[
  {
    "artist": "Chris Seaman",
    "cardClass": "PRIEST",
    "collectible": true,
    "cost": 7,
    "dbfId": 43112,
    "flavor": "所有人，都来牌库这！",
    "id": "LOOT_008",
    "name": "心灵尖啸",
    "rarity": "EPIC",
    "set": "LOOTAPALOOZA",
    "spellSchool": "SHADOW",
    "text": "将所有随从洗入你对手的牌库。",
    "type": "SPELL"
  },
  {
    "artist": "Mauricio Herrera",
    "cardClass": "PRIEST",
    "collectible": true,
    "cost": 3,
    "dbfId": 45353,
    "flavor": "“如果你得了复活综合症，请打1。”",
    "id": "LOOT_187",
    "name": "暮光召唤",
    "rarity": "RARE",
    "referencedTags": [
      "DEATHRATTLE"
    ],
    "set": "LOOTAPALOOZA",
    "spellSchool": "SHADOW",
    "text": "召唤两个在本局对战中死亡，并具有<b>亡语</b>的友方随从的1/1复制。",
    "type": "SPELL"
  },
  {
    "artist": "Tyler Walpole",
    "attack": 0,
    "cardClass": "PRIEST",
    "collectible": true,
    "cost": 3,
    "dbfId": 45528,
    "durability": 0,
    "elite": true,
    "flavor": "死亡之翼手下的地精制造了它，但上面的彩虹光效是巨龙亲自加上的。",
    "health": 3,
    "id": "LOOT_209",
    "name": "巨龙之魂",
    "rarity": "LEGENDARY",
    "set": "LOOTAPALOOZA",
    "text": "你在一回合中施放三个法术后，召唤一条5/5的龙。",
    "type": "WEAPON"
  },
  {
    "artist": "Dan Scott",
    "cardClass": "PRIEST",
    "collectible": true,
    "cost": 3,
    "dbfId": 45759,
    "flavor": "“嘿，尝尝这个。”（咕嘟嘟）“这是什么？”“我也不知道，在实验室找到的。”",
    "id": "LOOT_278",
    "name": "未鉴定的药剂",
    "rarity": "COMMON",
    "set": "LOOTAPALOOZA",
    "spellSchool": "HOLY",
    "text": "使一个随从获得+2/+2。在你手牌中时获得额外效果。",
    "type": "SPELL"
  },
  {
    "artist": "Mauricio Herrera",
    "cardClass": "PRIEST",
    "collectible": true,
    "cost": 1,
    "dbfId": 45979,
    "flavor": "她更喜欢管这叫作“心灵抚摸”。",
    "id": "LOOT_353",
    "name": "灵能窥探",
    "rarity": "COMMON",
    "set": "LOOTAPALOOZA",
    "spellSchool": "SHADOW",
    "text": "复制你对手的牌库中的一张法术牌，并将其置入你的\n手牌。",
    "type": "SPELL"
  },
  {
    "artist": "Alex Horley Orlandelli",
    "attack": 3,
    "cardClass": "PRIEST",
    "collectible": true,
    "cost": 4,
    "dbfId": 45899,
    "flavor": "“它将在暮光散去时醒来。”——说的就像谁不是一样。",
    "health": 3,
    "id": "LOOT_410",
    "mechanics": [
      "BATTLECRY"
    ],
    "name": "破晓之龙",
    "race": "DRAGON",
    "races": [
      "DRAGON"
    ],
    "rarity": "RARE",
    "set": "LOOTAPALOOZA",
    "text": "<b>战吼：</b>\n如果你的手牌中有龙牌，则对所有其他随从造成3点伤害。",
    "type": "MINION"
  },
  {
    "artist": "Tyler West Studio",
    "cardClass": "PRIEST",
    "collectible": true,
    "cost": 7,
    "dbfId": 46307,
    "flavor": "“第八颗石头是洁白的钻石，珍贵的宝石激励纯粹的信仰。低声的祈祷可以让逝者苏生，但没人知道要付出怎样的代价。”——《魔石》",
    "id": "LOOT_507",
    "name": "小型法术钻石",
    "rarity": "RARE",
    "set": "LOOTAPALOOZA",
    "spellSchool": "HOLY",
    "text": "复活两个不同的友方随从。<i>（施放四个法术后升级。）</i>",
    "type": "SPELL"
  },
  {
    "artist": "Tooth",
    "attack": 2,
    "cardClass": "PRIEST",
    "collectible": true,
    "cost": 3,
    "dbfId": 46460,
    "flavor": "巨龙们把他留在身边只是为了将来当点心吃掉。",
    "health": 4,
    "id": "LOOT_528",
    "mechanics": [
      "BATTLECRY"
    ],
    "name": "暮光侍僧",
    "rarity": "EPIC",
    "set": "LOOTAPALOOZA",
    "targetingArrowText": "交换攻击力。",
    "text": "<b>战吼：</b>如果你的手牌中有龙牌，则将本随从的攻击力与另一个随从交换。",
    "type": "MINION"
  },
  {
    "artist": "E. M. Gist",
    "attack": 2,
    "cardClass": "PRIEST",
    "collectible": true,
    "cost": 3,
    "dbfId": 46495,
    "flavor": "你听到石像鬼身体里有硬币的叮当声……这意味着什么？",
    "health": 2,
    "id": "LOOT_534",
    "mechanics": [
      "DEATHRATTLE"
    ],
    "name": "镀金的石像鬼",
    "race": "UNDEAD",
    "races": [
      "UNDEAD"
    ],
    "rarity": "COMMON",
    "set": "LOOTAPALOOZA",
    "text": "<b>亡语：</b>将一张幸运币置入你的手牌。",
    "type": "MINION"
  },
  {
    "artist": "Daren Bader",
    "attack": 6,
    "cardClass": "PRIEST",
    "collectible": true,
    "cost": 7,
    "dbfId": 46544,
    "elite": true,
    "flavor": "他从冒险者身上学到了最终极的时间魔法：回档。",
    "health": 6,
    "id": "LOOT_538",
    "mechanics": [
      "BATTLECRY"
    ],
    "name": "坦普卢斯",
    "race": "DRAGON",
    "races": [
      "DRAGON"
    ],
    "rarity": "LEGENDARY",
    "set": "LOOTAPALOOZA",
    "text": "<b>战吼：</b>在本回合结束后，你的对手连续行动两个回合。然后你行动两个回合。",
    "type": "MINION"
  }
]