[
  {
    "armor": 5,
    "artist": "Jim Nelson",
    "cardClass": "HUNTER",
    "collectible": true,
    "cost": 6,
    "dbfId": 67803,
    "elite": true,
    "flavor": "塔维什离开了家，他要走出自己的一条路。可这条路指引他走回了奥特兰克，继续和霜狼战斗。",
    "health": 30,
    "heroPowerDbfId": 67807,
    "id": "AV_113",
    "mechanics": [
      "BATTLECRY",
      "DISCOVER"
    ],
    "name": "野兽追猎者塔维什",
    "rarity": "LEGENDARY",
    "referencedTags": [
      "SECRET"
    ],
    "set": "ALTERAC_VALLEY",
    "text": "<b>战吼：</b><b>发现</b>并施放两张强化的<b>奥秘</b>牌。",
    "type": "HERO"
  },
  {
    "artist": "J. Paick & K. Turovec",
    "cardClass": "HUNTER",
    "collectible": true,
    "cost": 2,
    "dbfId": 71321,
    "flavor": "野蛮时代画风最野蛮的建筑。",
    "howToEarnGolden": "在奥特兰克获取荣誉点数以获得该奖励。",
    "id": "AV_147",
    "name": "丹巴达尔碉堡",
    "rarity": "RARE",
    "referencedTags": [
      "SECRET"
    ],
    "set": "ALTERAC_VALLEY",
    "text": "在你的回合结束时，抽一张<b>奥秘</b>牌并将其法力值消耗变为（1）点。持续3回合。",
    "type": "SPELL"
  },
  {
    "artist": "Jim Nelson",
    "cardClass": "HUNTER",
    "collectible": true,
    "cost": 4,
    "dbfId": 67241,
    "flavor": "一步踏错，步步踏错。",
    "id": "AV_224",
    "name": "布置陷阱",
    "rarity": "EPIC",
    "referencedTags": [
      "HONORABLE_KILL",
      "SECRET"
    ],
    "set": "ALTERAC_VALLEY",
    "text": "对一个随从造成$3点伤害，从你的牌库中施放一个<b>奥秘</b>。<b>荣誉消灭：</b>改为施放两个。",
    "type": "SPELL"
  },
  {
    "artist": "Matt Dixon",
    "cardClass": "HUNTER",
    "collectible": true,
    "cost": 2,
    "dbfId": 67243,
    "flavor": "我眼睁睁地看着猎人在我面前布下了陷阱，却还是踩了上去。",
    "id": "AV_226",
    "mechanics": [
      "SECRET"
    ],
    "name": "冰霜陷阱",
    "rarity": "EPIC",
    "set": "ALTERAC_VALLEY",
    "spellSchool": "FROST",
    "text": "<b>奥秘：</b>当你的对手施放一个法术时，改为将其移回拥有者的手牌，并且法力值消耗增加（1）点。",
    "type": "SPELL"
  },
  {
    "artist": "Studio Hive",
    "attack": 2,
    "cardClass": "HUNTER",
    "collectible": true,
    "cost": 2,
    "dbfId": 67574,
    "durability": 0,
    "flavor": "你这话是什么意思？背后放箭毫无荣誉可言？！",
    "health": 2,
    "id": "AV_244",
    "mechanics": [
      "HONORABLE_KILL",
      "TRIGGER_VISUAL"
    ],
    "name": "觅血者",
    "rarity": "COMMON",
    "set": "ALTERAC_VALLEY",
    "text": "<b>荣誉消灭：</b>获得+1/+1。",
    "type": "WEAPON"
  },
  {
    "artist": "Anton Zemskov",
    "cardClass": "HUNTER",
    "collectible": true,
    "cost": 3,
    "dbfId": 70103,
    "flavor": "最好的朋友其实从未远离。",
    "id": "AV_333",
    "mechanics": [
      "DISCOVER"
    ],
    "name": "复活宠物",
    "rarity": "RARE",
    "set": "ALTERAC_VALLEY",
    "spellSchool": "NATURE",
    "text": "<b>发现</b>一只在本局对战中死亡的友方野兽，并召唤该随从。",
    "type": "SPELL"
  },
  {
    "artist": "Jim Nelson",
    "attack": 4,
    "cardClass": "HUNTER",
    "collectible": true,
    "cost": 4,
    "dbfId": 70104,
    "flavor": "咩咩咩！以矮人与胡须之名，雷矛氏族屹立不倒！",
    "health": 3,
    "id": "AV_334",
    "mechanics": [
      "DEATHRATTLE",
      "RUSH"
    ],
    "name": "雷矛军用山羊",
    "race": "BEAST",
    "races": [
      "BEAST"
    ],
    "rarity": "RARE",
    "set": "ALTERAC_VALLEY",
    "text": "<b>突袭</b>，<b>亡语：</b>你的下一张野兽牌法力值消耗减少（2）点。",
    "type": "MINION"
  },
  {
    "artist": "Matt Dixon",
    "attack": 4,
    "cardClass": "HUNTER",
    "collectible": true,
    "cost": 3,
    "dbfId": 70105,
    "flavor": "别看它只是一只羊，羊儿的聪明难以想象。",
    "health": 3,
    "id": "AV_335",
    "mechanics": [
      "BATTLECRY"
    ],
    "name": "驯羊师",
    "rarity": "COMMON",
    "referencedTags": [
      "SECRET",
      "STEALTH"
    ],
    "set": "ALTERAC_VALLEY",
    "text": "<b>战吼：</b>如果你控制一个<b>奥秘</b>，便获得+1/+1和<b>潜行</b>。",
    "type": "MINION"
  },
  {
    "artist": "Mike Sass",
    "attack": 5,
    "cardClass": "HUNTER",
    "collectible": true,
    "cost": 9,
    "dbfId": 70106,
    "elite": true,
    "flavor": "“穆维里克！你倚仗的不是飞行技术，是阵营人数。”",
    "health": 4,
    "id": "AV_336",
    "mechanics": [
      "BATTLECRY"
    ],
    "name": "空军指挥官艾克曼",
    "rarity": "LEGENDARY",
    "referencedTags": [
      "RUSH"
    ],
    "set": "ALTERAC_VALLEY",
    "text": "<b>战吼：</b>从你的牌库中召唤一只野兽并使其获得<b>突袭</b>。如果它在本回合中消灭了一个随从，重复此效果。",
    "type": "MINION"
  },
  {
    "artist": "Todd Harris",
    "attack": 5,
    "cardClass": "HUNTER",
    "collectible": true,
    "cost": 7,
    "dbfId": 70245,
    "flavor": "如果它们想要你的野餐篮，我建议你乖乖地交出去。",
    "health": 6,
    "id": "AV_337",
    "mechanics": [
      "DEATHRATTLE",
      "TAUNT"
    ],
    "name": "山岭野熊",
    "race": "BEAST",
    "races": [
      "BEAST"
    ],
    "rarity": "COMMON",
    "set": "ALTERAC_VALLEY",
    "text": "<b>嘲讽</b>，<b>亡语：</b>召唤两只2/4并具有<b>嘲讽</b>的山熊宝宝。",
    "type": "MINION"
  },
  {
    "artist": "L. Lullabi & A. Zemskov",
    "cardClass": "HUNTER",
    "collectible": true,
    "cost": 2,
    "dbfId": 71231,
    "flavor": "不要和猎人做邻居。",
    "id": "ONY_008",
    "isMiniSet": true,
    "name": "狂怒之嚎",
    "rarity": "COMMON",
    "set": "ALTERAC_VALLEY",
    "text": "抽一张牌。重复，直到你拥有至少三张牌。",
    "type": "SPELL"
  },
  {
    "artist": "Anzka Nguyen",
    "attack": 4,
    "cardClass": "HUNTER",
    "collectible": true,
    "cost": 5,
    "dbfId": 71232,
    "flavor": "“我来给你们取名字吧，你就叫贴身之裤，你叫抱抱之泡泡，你叫可爱之蛋糕，还有你……”",
    "health": 4,
    "id": "ONY_009",
    "isMiniSet": true,
    "mechanics": [
      "BATTLECRY"
    ],
    "name": "宠物收集者",
    "rarity": "COMMON",
    "set": "ALTERAC_VALLEY",
    "text": "<b>战吼：</b>从你的牌库中召唤一只法力值消耗小于或等于（5）点的野兽。",
    "type": "MINION"
  },
  {
    "artist": "Melvin Chan",
    "cardClass": "HUNTER",
    "collectible": true,
    "cost": 2,
    "dbfId": 71233,
    "flavor": "<i>*仅对小型龙类有效。</i>",
    "id": "ONY_010",
    "isMiniSet": true,
    "mechanics": [
      "HONORABLE_KILL"
    ],
    "name": "灭龙射击",
    "rarity": "RARE",
    "set": "ALTERAC_VALLEY",
    "text": "造成$2点伤害。<b>荣誉消灭：</b>将一张灭龙射击置入你的手牌。",
    "type": "SPELL"
  }
]