[
  {
    "artist": "Konstantin Turovec",
    "cardClass": "PRIEST",
    "collectible": true,
    "cost": 1,
    "dbfId": 106521,
    "flavor": "绝品的茗茶，还是致命的毒草？",
    "id": "VAC_404",
    "name": "夜影花茶",
    "rarity": "RARE",
    "set": "ISLAND_VACATION",
    "spellSchool": "SHADOW",
    "text": "对一个随从造成$2点伤害。对你的英雄造成$2点伤害。<i>（还剩3杯！）</i>",
    "type": "SPELL"
  },
  {
    "artist": "Matt Dixon",
    "cardClass": "PRIEST",
    "collectible": true,
    "cost": 3,
    "dbfId": 106640,
    "flavor": "如果你调皮到一定程度，冬天爷爷给你的礼物就是这个了。",
    "id": "VAC_414",
    "name": "炽热火炭",
    "rarity": "COMMON",
    "set": "ISLAND_VACATION",
    "spellSchool": "FIRE",
    "text": "对所有敌人造成$2点伤害。如果你的英雄在本回合受到过伤害，再造成$1点。",
    "type": "SPELL"
  },
  {
    "artist": "Juan Calle",
    "cardClass": "PRIEST",
    "collectible": true,
    "cost": 6,
    "dbfId": 106705,
    "flavor": "你会成为新造的人。",
    "id": "VAC_417",
    "name": "感官侵夺",
    "rarity": "EPIC",
    "set": "ISLAND_VACATION",
    "spellSchool": "SHADOW",
    "text": "召唤一个敌方随从的一个复制。如果你的生命值小于或等于20点，消灭本体。",
    "type": "SPELL"
  },
  {
    "artist": "Max Grecke",
    "attack": 5,
    "cardClass": "PRIEST",
    "collectible": true,
    "cost": 5,
    "dbfId": 106708,
    "flavor": "蒸至“肉烂脱骨”即可。",
    "health": 5,
    "id": "VAC_418",
    "mechanics": [
      "TAUNT"
    ],
    "name": "桑拿常客",
    "race": "UNDEAD",
    "races": [
      "UNDEAD"
    ],
    "rarity": "RARE",
    "set": "ISLAND_VACATION",
    "text": "<b>嘲讽</b>。你的英雄每在你的回合受到一次伤害，本牌的法力值消耗便减少（1）点。",
    "type": "MINION"
  },
  {
    "artist": "Jason Kang",
    "cardClass": "PRIEST",
    "collectible": true,
    "cost": 1,
    "dbfId": 106709,
    "flavor": "你刚刚说了灸灸对吧！",
    "id": "VAC_419",
    "name": "针灸",
    "rarity": "COMMON",
    "set": "ISLAND_VACATION",
    "spellSchool": "SHADOW",
    "text": "对双方英雄造成$4点伤害。",
    "type": "SPELL"
  },
  {
    "artist": "Max Grecke",
    "attack": 4,
    "cardClass": "PRIEST",
    "collectible": true,
    "cost": 4,
    "dbfId": 106713,
    "elite": true,
    "faction": "ALLIANCE",
    "flavor": "我算到了……你这次算命的过程会非常愉快！",
    "health": 4,
    "id": "VAC_420",
    "mechanics": [
      "BATTLECRY"
    ],
    "name": "纳瑞安·柔想",
    "rarity": "LEGENDARY",
    "set": "ISLAND_VACATION",
    "text": "<b>战吼：</b>获取两张预知命运。预知命运为你牌库顶的牌的复制。",
    "type": "MINION"
  },
  {
    "artist": "James Ryman",
    "attack": 4,
    "cardClass": "PRIEST",
    "collectible": true,
    "cost": 5,
    "dbfId": 106724,
    "flavor": "这种暮光太暗，那种暮光又太亮，而灵媒师居于两者中间。",
    "health": 5,
    "id": "VAC_423",
    "mechanics": [
      "BATTLECRY",
      "TAUNT"
    ],
    "name": "暮光灵媒师",
    "rarity": "EPIC",
    "set": "ISLAND_VACATION",
    "text": "<b>嘲讽</b>。<b>战吼：</b>将你牌库顶的一张牌的法力值消耗变为（1）点。",
    "type": "MINION"
  },
  {
    "artist": "Ramzy Kamen",
    "cardClass": "PRIEST",
    "collectible": true,
    "cost": 3,
    "dbfId": 109260,
    "flavor": "安息吧，编出来的那个谁。",
    "id": "VAC_457",
    "name": "安息",
    "rarity": "RARE",
    "set": "ISLAND_VACATION",
    "spellSchool": "SHADOW",
    "text": "每个玩家分别召唤其在本局对战中死亡的法力值消耗最高的随从。",
    "type": "SPELL"
  },
  {
    "artist": "James Ryman",
    "attack": 2,
    "cardClass": "PRIEST",
    "collectible": true,
    "cost": 1,
    "dbfId": 105815,
    "flavor": "用力。用力！用！力！哎呀。用力？",
    "health": 4,
    "id": "VAC_512",
    "mechanics": [
      "TRIGGER_VISUAL"
    ],
    "name": "心灵按摩师",
    "race": "UNDEAD",
    "races": [
      "UNDEAD",
      "PIRATE"
    ],
    "rarity": "COMMON",
    "set": "ISLAND_VACATION",
    "text": "每当本随从受到伤害，对你的英雄造成等量的伤害。",
    "type": "MINION"
  },
  {
    "artist": "Grafit",
    "attack": 3,
    "cardClass": "PRIEST",
    "collectible": true,
    "cost": 3,
    "dbfId": 108887,
    "elite": true,
    "flavor": "请冰冷整脊师为你调理一下吧，你也可以像沃金一样惬意！",
    "health": 3,
    "id": "VAC_957",
    "mechanics": [
      "BATTLECRY"
    ],
    "name": "惬意的沃金",
    "rarity": "LEGENDARY",
    "set": "ISLAND_VACATION",
    "targetingArrowText": "选择2个随从，交换其属性值。",
    "text": "<b>猎人游客</b>\n<b>战吼：</b>选择2个随从，交换其属性值。",
    "type": "MINION"
  },
  {
    "artist": "Mooncolony",
    "cardClass": "PRIEST",
    "collectible": true,
    "cost": 2,
    "dbfId": 110771,
    "flavor": "每年的这个时节去这里逛逛挺好的。只要别去城外那道死亡之痕就行。",
    "id": "WORK_017",
    "isMiniSet": true,
    "name": "银月城宣传单",
    "rarity": "RARE",
    "referencedTags": [
      "IMMUNE"
    ],
    "set": "ISLAND_VACATION",
    "spellSchool": "HOLY",
    "text": "使一个随从获得在本回合中<b>免疫</b>和+2/+2。\n<i>（每回合翻面。）</i>",
    "type": "SPELL"
  },
  {
    "artist": "Guillaume Beauchêne",
    "attack": 4,
    "cardClass": "PRIEST",
    "collectible": true,
    "cost": 2,
    "dbfId": 110849,
    "flavor": "“财富会紧紧跟着你，如影随形！”",
    "health": 4,
    "id": "WORK_031",
    "isMiniSet": true,
    "mechanics": [
      "BATTLECRY"
    ],
    "name": "暴富特使",
    "race": "DRAENEI",
    "races": [
      "DRAENEI"
    ],
    "rarity": "RARE",
    "set": "ISLAND_VACATION",
    "text": "<b>战吼：</b>将你手牌中法力值消耗最高的牌置于你的牌库顶。",
    "type": "MINION"
  },
  {
    "artist": "L. Lullabi & K. Turovec",
    "attack": 4,
    "cardClass": "PRIEST",
    "collectible": true,
    "cost": 3,
    "dbfId": 110850,
    "flavor": "“财富……紧跟……如影……随行！好，懂了！”",
    "health": 3,
    "id": "WORK_032",
    "isMiniSet": true,
    "mechanics": [
      "BATTLECRY"
    ],
    "name": "影随员工",
    "race": "UNDEAD",
    "races": [
      "UNDEAD"
    ],
    "rarity": "COMMON",
    "set": "ISLAND_VACATION",
    "text": "<b>战吼：</b>如果你的\n英雄在本回合受到过伤害，召唤一个本随从的复制。",
    "type": "MINION"
  }
]