[
  {
    "artist": "Wayne Wu",
    "cardClass": "SHAMAN",
    "collectible": true,
    "cost": 2,
    "dbfId": 48051,
    "flavor": "哎哟我这暴脾气。",
    "id": "BOT_093",
    "name": "元素反应",
    "rarity": "COMMON",
    "set": "BOOMSDAY",
    "spellSchool": "NATURE",
    "text": "抽一张牌。如果你在上个回合使用过元素牌，则复制抽到的牌。",
    "type": "SPELL"
  },
  {
    "artist": "Evgeniy Dlinnov",
    "cardClass": "SHAMAN",
    "collectible": true,
    "cost": 0,
    "dbfId": 48798,
    "flavor": "在萨满祭司实验室工作只有一个要求，那就是——稳。",
    "id": "BOT_246",
    "mechanics": [
      "OVERLOAD"
    ],
    "name": "瓶装闪电",
    "overload": 2,
    "rarity": "COMMON",
    "set": "BOOMSDAY",
    "spellSchool": "NATURE",
    "text": "对所有随从造成$1点伤害。\n<b>过载：</b>（2）",
    "type": "SPELL"
  },
  {
    "artist": "Daria Tuzova",
    "attack": 2,
    "cardClass": "SHAMAN",
    "collectible": true,
    "cost": 2,
    "dbfId": 49162,
    "flavor": "伊莱克特拉把她的元素藏在了云端里。",
    "health": 3,
    "id": "BOT_533",
    "mechanics": [
      "BATTLECRY"
    ],
    "name": "凶恶的雨云",
    "race": "ELEMENTAL",
    "races": [
      "ELEMENTAL"
    ],
    "rarity": "COMMON",
    "set": "BOOMSDAY",
    "text": "<b>战吼：</b>随机将一张元素牌置入你的手牌。",
    "type": "MINION"
  }
]