[
  {
    "artist": "Konstantin Turovec",
    "cardClass": "WARLOCK",
    "collectible": true,
    "cost": 1,
    "dbfId": 41856,
    "elite": true,
    "flavor": "探险者：“但是，古尔丹，代价是什么呢？”\n古尔丹：“弃掉…六张牌…”",
    "id": "UNG_829",
    "mechanics": [
      "QUEST"
    ],
    "name": "拉卡利献祭",
    "questReward": "UNG_829t1",
    "rarity": "LEGENDARY",
    "set": "UNGORO",
    "text": "<b>任务：</b>弃掉六张牌。\n<b>奖励：</b>虚空传送门。",
    "type": "SPELL"
  },
  {
    "artist": "Anton Zemskov",
    "attack": 2,
    "cardClass": "WARLOCK",
    "collectible": true,
    "cost": 2,
    "dbfId": 41876,
    "elite": true,
    "flavor": "主人弃我千百遍，我待主人如初恋。",
    "health": 2,
    "id": "UNG_836",
    "mechanics": [
      "InvisibleDeathrattle"
    ],
    "name": "萨瓦丝女王",
    "race": "BEAST",
    "races": [
      "BEAST"
    ],
    "rarity": "LEGENDARY",
    "set": "UNGORO",
    "text": "每当你弃掉这张牌时，使其获得+2/+2，并将其移回你的手牌。",
    "type": "MINION"
  }
]